{
	"name": "FirstPipeline",
	"properties": {
		"activities": [
			{
				"name": "Healthy_Wealthy_Happy_Lucky",
				"description": "Thank you Universe :)",
				"type": "Wait",
				"dependsOn": [],
				"userProperties": [],
				"typeProperties": {
					"waitTimeInSeconds": 1
				}
			},
			{
				"name": "LoadAllFIles",
				"type": "GetMetadata",
				"dependsOn": [
					{
						"activity": "Healthy_Wealthy_Happy_Lucky",
						"dependencyConditions": [
							"Succeeded"
						]
					}
				],
				"policy": {
					"timeout": "0.12:00:00",
					"retry": 0,
					"retryIntervalInSeconds": 30,
					"secureOutput": false,
					"secureInput": false
				},
				"userProperties": [],
				"typeProperties": {
					"dataset": {
						"referenceName": "ds_csv_060426",
						"type": "DatasetReference"
					},
					"fieldList": [
						"childItems"
					],
					"storeSettings": {
						"type": "AzureBlobStorageReadSettings",
						"enablePartitionDiscovery": false
					},
					"formatSettings": {
						"type": "DelimitedTextReadSettings"
					}
				}
			},
			{
				"name": "FilterOnlyCSV",
				"type": "Filter",
				"dependsOn": [
					{
						"activity": "LoadAllFIles",
						"dependencyConditions": [
							"Succeeded"
						]
					}
				],
				"userProperties": [],
				"typeProperties": {
					"items": {
						"value": "@activity('LoadAllFIles').output.childItems",
						"type": "Expression"
					},
					"condition": {
						"value": "@contains(item().name,'CSV')",
						"type": "Expression"
					}
				}
			},
			{
				"name": "ForEachCSVFiles",
				"type": "ForEach",
				"dependsOn": [
					{
						"activity": "FilterOnlyCSV",
						"dependencyConditions": [
							"Succeeded"
						]
					}
				],
				"userProperties": [],
				"typeProperties": {
					"items": {
						"value": "@activity('FilterOnlyCSV').output.value",
						"type": "Expression"
					},
					"isSequential": true,
					"activities": [
						{
							"name": "LoadIntoStage",
							"type": "Copy",
							"dependsOn": [],
							"policy": {
								"timeout": "0.12:00:00",
								"retry": 0,
								"retryIntervalInSeconds": 30,
								"secureOutput": false,
								"secureInput": false
							},
							"userProperties": [],
							"typeProperties": {
								"source": {
									"type": "DelimitedTextSource",
									"storeSettings": {
										"type": "AzureBlobStorageReadSettings",
										"recursive": true,
										"enablePartitionDiscovery": false
									},
									"formatSettings": {
										"type": "DelimitedTextReadSettings"
									}
								},
								"sink": {
									"type": "SqlServerSink",
									"preCopyScript": "truncate table Employee_Stage",
									"writeBehavior": "insert",
									"sqlWriterUseTableLock": false
								},
								"enableStaging": false,
								"translator": {
									"type": "TabularTranslator",
									"typeConversion": true,
									"typeConversionSettings": {
										"allowDataTruncation": true,
										"treatBooleanAsNumber": false
									}
								}
							},
							"inputs": [
								{
									"referenceName": "ds_csv_src_060426",
									"type": "DatasetReference",
									"parameters": {
										"FileName": {
											"value": "@item().name",
											"type": "Expression"
										}
									}
								}
							],
							"outputs": [
								{
									"referenceName": "ds_tgt_sql_060426",
									"type": "DatasetReference"
								}
							]
						},
						{
							"name": "CallSP",
							"type": "SqlServerStoredProcedure",
							"dependsOn": [
								{
									"activity": "LoadIntoStage",
									"dependencyConditions": [
										"Succeeded"
									]
								}
							],
							"policy": {
								"timeout": "0.12:00:00",
								"retry": 0,
								"retryIntervalInSeconds": 30,
								"secureOutput": false,
								"secureInput": false
							},
							"userProperties": [],
							"typeProperties": {
								"storedProcedureName": "[dbo].[MergeStageIntoActual]"
							},
							"linkedServiceName": {
								"referenceName": "ls_sql_060426",
								"type": "LinkedServiceReference"
							}
						}
					]
				}
			}
		],
		"annotations": [],
		"lastPublishTime": "2026-04-03T12:44:22Z"
	},
	"type": "Microsoft.DataFactory/factories/pipelines"
}